[
    {
        "file": "temp/flat/Ettie537_Farrell962_d8638449-e632-1ac7-6695-eb60c8773813/Ettie537_Farrell962_d8638449-e632-1ac7-6695-eb60c8773813_22-08-2021.txt",
        "query": "What specific oral hygiene issues did Ettie537 Farrell962 have that required the removal of both supragingival and subgingival plaque and calculus?",
        "synthetic query": "What specific oral hygiene issues did the patient have that required the removal of both supragingival and subgingival plaque and calculus?",
        "information": [
            "Ettie537 Farrell962 had multiple instances of oral hygiene issues that required the removal of both supragingival and subgingival plaque and calculus. This was documented on 08-09-2024, 22-08-2021, and 05-08-2018."
        ],
        "nodes": [
            "Ettie537_Farrell962_d8638449-e632-1ac7-6695-eb60c8773813_08-09-2024.txt",
            "Nichol11_Stiedemann542_d3526c15-a6eb-ec69-d2ce-7f4dfac7fc5e_23-04-2023.txt",
            "Ettie537_Farrell962_d8638449-e632-1ac7-6695-eb60c8773813_22-08-2021.txt",
            "Ettie537_Farrell962_d8638449-e632-1ac7-6695-eb60c8773813_05-08-2018.txt",
            "Aleisha941_Treutel973_2d799deb-df07-0c4a-8692-42cce7595251_11-04-2022.txt",
            "Aleisha941_Treutel973_2d799deb-df07-0c4a-8692-42cce7595251_17-06-2024.txt"
        ],
        "synthesized information": "Patient had multiple instances of oral hygiene issues requiring removal of both supragingival and subgingival plaque and calculus. This was documented on Encounter Dates [DATE1], [DATE2], and [DATE3].",
        "review": "",
        "response": "The provided information indicates that the patient required the removal of both supragingival (above the gum line) and subgingival (below the gum line) plaque and calculus, which suggests they had significant build-ups of these substances. These deposits can lead to various oral hygiene issues such as gingivitis or periodontal disease, characterized by inflammation and infection of the gums that may extend to deeper supporting structures like the bone if left untreated. However, specific details about the nature of these issues (like whether it was gingivitis, periodontitis, or another condition) are not provided in the given information. The treatments were documented on Encounter Dates [DATE1], [DATE2], and [DATE3]."
    },
    {
        "file": "temp/flat/Ettie537_Farrell962_d8638449-e632-1ac7-6695-eb60c8773813/Ettie537_Farrell962_d8638449-e632-1ac7-6695-eb60c8773813_21-08-2022.txt",
        "query": "What was Ettie537 Farrell962's BMI percentile according to the observations made on the encounter date of 21-08-2022?",
        "synthetic query": "What was the patient's BMI percentile according to the observations made on [DATE]?",
        "information": [
            "Ettie537 Farrell962's BMI percentile on the encounter date of 21-08-2022 was 51.37%."
        ],
        "nodes": [
            "Ettie537_Farrell962_d8638449-e632-1ac7-6695-eb60c8773813_21-08-2022.txt",
            "Ettie537_Farrell962_d8638449-e632-1ac7-6695-eb60c8773813_27-08-2023.txt",
            "Ettie537_Farrell962_d8638449-e632-1ac7-6695-eb60c8773813_04-08-2019.txt",
            "Ettie537_Farrell962_d8638449-e632-1ac7-6695-eb60c8773813_09-08-2020.txt",
            "Ettie537_Farrell962_d8638449-e632-1ac7-6695-eb60c8773813_24-07-2016.txt",
            "Ettie537_Farrell962_d8638449-e632-1ac7-6695-eb60c8773813_15-08-2021.txt"
        ],
        "synthesized information": "The patient's BMI percentile on [DATE] was 51%. This information is based on medical observations.",
        "review": "",
        "response": "The patient's BMI percentile on the specified date was 51% according to the medical observations."
    },
    {
        "file": "temp/flat/Ettie537_Farrell962_d8638449-e632-1ac7-6695-eb60c8773813/Ettie537_Farrell962_d8638449-e632-1ac7-6695-eb60c8773813_21-08-2022.txt",
        "query": "According to the observations noted on August 21, 2022, what was the self-reported pain severity score for Ettie537 Farrell962 using a verbal numeric rating scale from 0-10?",
        "synthetic query": "What was the self-reported pain severity score for a patient using a verbal numeric rating scale from 0-10 on [DATE]?",
        "information": [
            "The self-reported pain severity score for Ettie537 Farrell962 on August 21, 2022 using a verbal numeric rating scale from 0-10 was 1.00."
        ],
        "nodes": [
            "Ettie537_Farrell962_d8638449-e632-1ac7-6695-eb60c8773813_15-08-2021.txt",
            "Ettie537_Farrell962_d8638449-e632-1ac7-6695-eb60c8773813_21-08-2022.txt"
        ],
        "synthesized information": "On [DATE], the self-reported pain severity score for a patient using a verbal numeric rating scale from 0-10 was 1.",
        "review": "",
        "response": "The self-reported pain severity score for the patient using a verbal numeric rating scale from 0-10 on [DATE] was 1."
    },
    {
        "file": "temp/flat/Ettie537_Farrell962_d8638449-e632-1ac7-6695-eb60c8773813/Ettie537_Farrell962_d8638449-e632-1ac7-6695-eb60c8773813_21-08-2022.txt",
        "query": "Based on the provided medical record, what were Ettie537 Farrell962's systolic and diastolic blood pressure readings observed during the examination on August 21, 2022?",
        "synthetic query": "What were the systolic and diastolic blood pressure readings observed for the patient during the examination on [DATE]?",
        "information": [
            "Ettie537 Farrell962's systolic and diastolic blood pressure readings on August 21, 2022 were 119.00 mm[Hg] and 82.00 mm[Hg], respectively."
        ],
        "nodes": [
            "Ettie537_Farrell962_d8638449-e632-1ac7-6695-eb60c8773813_21-08-2022.txt",
            "Ettie537_Farrell962_d8638449-e632-1ac7-6695-eb60c8773813_09-08-2020.txt",
            "Ettie537_Farrell962_d8638449-e632-1ac7-6695-eb60c8773813_04-08-2019.txt",
            "Ettie537_Farrell962_d8638449-e632-1ac7-6695-eb60c8773813_01-09-2024.txt",
            "Wade235_Emmerich580_13cc1678-474c-7932-a719-c64f3a7adc9f_21-09-2022.txt",
            "Ettie537_Farrell962_d8638449-e632-1ac7-6695-eb60c8773813_24-07-2016.txt"
        ],
        "synthesized information": "The patient's systolic and diastolic blood pressure readings on [DATE] were 119 mm[Hg] and 82 mm[Hg], respectively.",
        "review": "",
        "response": "The patient's systolic blood pressure reading was 119 mm[Hg] and the diastolic blood pressure reading was 82 mm[Hg] during the examination on [DATE]."
    },
    {
        "file": "temp/flat/Ettie537_Farrell962_d8638449-e632-1ac7-6695-eb60c8773813/Ettie537_Farrell962_d8638449-e632-1ac7-6695-eb60c8773813_27-08-2023.txt",
        "query": "Based on the observations, what is Ettie537 Farrell962's Body Mass Index (BMI) and how does it compare to her age and sex percentile?",
        "synthetic query": "What is the patient's Body Mass Index (BMI) range and how does it compare to their age and sex percentile over different encounters?",
        "information": [
            "Here is the extracted Body Mass Index (BMI) information for Ettie537 Farrell962 from the provided context:\n\n- **Encounter Date:** 04-08-2019  \n  - Code is Body mass index (BMI) [Ratio]. Value is 15.91 kg/m2.\n  - Code is Body mass index (BMI) [Percentile] Per age and sex. Value is 67.47 %.\n\n- **Encounter Date:** 09-08-2020  \n  - Code is Body mass index (BMI) [Ratio]. Value is 16.48 kg/m2.\n  - Code is Body mass index (BMI) [Percentile] Per age and sex. Value is 71.72 %.\n\n- **Encounter Date:** 15-08-2021  \n  - Code is Body mass index (BMI) [Ratio]. Value is 16.36 kg/m2.\n  - Code is Body mass index (BMI) [Percentile] Per age and sex. Value is 61.39 %.\n\n- **Encounter Date:** 27-08-2023  \n  - Code is Body mass index (BMI) [Ratio]. Value is 17.24 kg/m2.\n  - Code is Body mass index (BMI) [Percentile] Per age and sex. Value is 56.23 %.\n\n- **Encounter Date:** 01-09-2024  \n  - Code is Body mass index (BMI) [Ratio]. Value is 18.69 kg/m2.\n  - Code is Body mass index (BMI) [Percentile] Per age and sex. Value is 66.99 %."
        ],
        "nodes": [
            "Ettie537_Farrell962_d8638449-e632-1ac7-6695-eb60c8773813_27-08-2023.txt",
            "Ettie537_Farrell962_d8638449-e632-1ac7-6695-eb60c8773813_15-08-2021.txt",
            "Ettie537_Farrell962_d8638449-e632-1ac7-6695-eb60c8773813_01-09-2024.txt",
            "Ettie537_Farrell962_d8638449-e632-1ac7-6695-eb60c8773813_04-08-2019.txt",
            "Ettie537_Farrell962_d8638449-e632-1ac7-6695-eb60c8773813_09-08-2020.txt",
            "Ettie537_Farrell962_d8638449-e632-1ac7-6695-eb60c8773813_24-07-2016.txt"
        ],
        "synthesized information": "The patient's Body Mass Index (BMI) has varied over different encounters as follows:\n\n- **[DATE]**: BMI is approximately 16 kg/m2, with a percentile of about 67%.\n- **[DATE]**: BMI is around 16.5 kg/m2, with a percentile of roughly 72%.\n- **[DATE]**: BMI is nearly 16.4 kg/m2, with a percentile of approximately 61%.\n- **[DATE]**: BMI is close to 17.2 kg/m2, with a percentile around 56%.\n- **[DATE]**: BMI is about 18.7 kg/m2, with a percentile of nearly 67%. \nThe BMI values range from approximately 16 to 19 kg/m2 and the percentiles vary between roughly 56% to 72%, relative to age and sex.",
        "review": "",
        "response": "Based on the provided information, the patient's Body Mass Index (BMI) has ranged from approximately 16 to 18.7 kg/m\u00b2 across different encounters. The BMI percentile, compared to others of the same age and sex, fluctuated between about 56% and 72%. This indicates that while the patient's BMI is relatively stable within a range considered underweight or low-normal (generally, a healthy weight for adults is considered to be in the range of 18.5-24.9 kg/m\u00b2), their position relative to peers has varied, suggesting some variability in how their body mass compares to age and sex norms over time."
    },
    {
        "file": "temp/flat/Ettie537_Farrell962_d8638449-e632-1ac7-6695-eb60c8773813/Ettie537_Farrell962_d8638449-e632-1ac7-6695-eb60c8773813_27-08-2023.txt",
        "query": "What were Ettie537 Farrell962's blood pressure readings during the encounter on 27-08-2023, and what was her reported pain severity level on a verbal numeric rating scale from 0 to 10?",
        "synthetic query": "What were the blood pressure readings and reported pain severity level on a verbal numeric rating scale from 0 to 10 during the encounter on [DATE]?",
        "information": [
            "Blood pressure readings for Ettie537 Farrell962 on 27-08-2023: Diastolic Blood Pressure was 86.00 mm[Hg] and Systolic Blood Pressure was 115.00 mm[Hg].",
            "Pain severity level on verbal numeric rating scale from 0 to 10 for Ettie537 Farrell962 on 27-08-2023 was reported as 2.00 {score}."
        ],
        "nodes": [
            "Ettie537_Farrell962_d8638449-e632-1ac7-6695-eb60c8773813_27-08-2023.txt",
            "Ettie537_Farrell962_d8638449-e632-1ac7-6695-eb60c8773813_21-08-2022.txt",
            "Ettie537_Farrell962_d8638449-e632-1ac7-6695-eb60c8773813_04-08-2019.txt",
            "Ettie537_Farrell962_d8638449-e632-1ac7-6695-eb60c8773813_15-08-2021.txt",
            "Ettie537_Farrell962_d8638449-e632-1ac7-6695-eb60c8773813_09-08-2020.txt",
            "Ettie537_Farrell962_d8638449-e632-1ac7-6695-eb60c8773813_29-07-2018.txt",
            "Ettie537_Farrell962_d8638449-e632-1ac7-6695-eb60c8773813_15-08-2021.txt",
            "Ettie537_Farrell962_d8638449-e632-1ac7-6695-eb60c8773813_27-08-2023.txt",
            "Ettie537_Farrell962_d8638449-e632-1ac7-6695-eb60c8773813_04-08-2019.txt",
            "Ettie537_Farrell962_d8638449-e632-1ac7-6695-eb60c8773813_01-09-2024.txt"
        ],
        "synthesized information": "The patient's blood pressure on [DATE] was a diastolic reading of 86 mm[Hg] and a systolic reading of 115 mm[Hg]. The reported pain severity level on the verbal numeric rating scale from 0 to 10 was 2.",
        "review": "",
        "response": "On [DATE], the patient's blood pressure readings were a systolic of 115 mm[Hg] and a diastolic of 86 mm[Hg]. The reported pain severity level on the verbal numeric rating scale from 0 to 10 was 2."
    },
    {
        "file": "temp/flat/Ettie537_Farrell962_d8638449-e632-1ac7-6695-eb60c8773813/Ettie537_Farrell962_d8638449-e632-1ac7-6695-eb60c8773813_27-08-2023.txt",
        "query": "Given that Ettie537 Farrell962 has never been married and has never smoked tobacco, how might these lifestyle factors influence her overall health status as of the encounter date?",
        "synthetic query": "How do the lifestyle factors of never smoking tobacco and regular dental care influence a patient's overall health status?",
        "information": [
            "Based on the provided context information, the following are the lifestyle factors influencing the overall health status of Ettie537 Farrell962:\n\n- **Tobacco smoking status:** Never smoked tobacco (finding) - This indicates that smoking is not a factor negatively impacting her health.\n\n- **Dental care procedures and consultations:**\n  - Completed Dental consultation and report (procedure)\n  - Completed Dental care (regime/therapy)\n  - Completed Removal of supragingival plaque and calculus from all teeth using dental instrument (procedure)\n  - Completed Removal of subgingival plaque and calculus from all teeth using dental instrument (procedure)\n  - Completed Examination of gingivae (procedure)\n  - Completed Oral health education (procedure)\n\nThese procedures suggest regular oral hygiene maintenance, which positively influences her overall health status by preventing complications such as periodontal disease.\n\n- **Medication reconciliation:** This procedure was completed on several occasions, indicating that any medications she might be taking are regularly reviewed for effectiveness and potential side effects. This can help in managing her health effectively without adverse drug interactions.\n\nThe above information indicates a proactive approach towards maintaining good oral hygiene and monitoring medication use, both of which contribute positively to Ettie537 Farrell962's overall health status."
        ],
        "nodes": [
            "Ettie537_Farrell962_d8638449-e632-1ac7-6695-eb60c8773813_24-05-2020.txt",
            "Ettie537_Farrell962_d8638449-e632-1ac7-6695-eb60c8773813_15-08-2021.txt",
            "Ettie537_Farrell962_d8638449-e632-1ac7-6695-eb60c8773813_05-08-2018.txt",
            "Ettie537_Farrell962_d8638449-e632-1ac7-6695-eb60c8773813_04-08-2019.txt",
            "Ettie537_Farrell962_d8638449-e632-1ac7-6695-eb60c8773813_01-09-2024.txt",
            "Ettie537_Farrell962_d8638449-e632-1ac7-6695-eb60c8773813_24-07-2016.txt",
            "Ettie537_Farrell962_d8638449-e632-1ac7-6695-eb60c8773813_08-09-2024.txt"
        ],
        "synthesized information": "The patient's never having smoked tobacco indicates that smoking is not negatively impacting their health. Regular dental care procedures, including consultations and oral hygiene maintenance, contribute positively to overall health by preventing complications such as periodontal disease. Medication reconciliation was completed multiple times, indicating effective management of any medications without adverse drug interactions.",
        "review": "",
        "response": "The lifestyle factors of never smoking tobacco and maintaining regular dental care have significant positive impacts on a patient's overall health status. Never having smoked tobacco protects the patient from a wide range of negative health outcomes associated with smoking, such as lung cancer, heart disease, respiratory issues, and other chronic conditions that can be exacerbated or caused by smoking.\n\nRegular dental care contributes to the maintenance of good oral health, which is linked to lower risks of systemic diseases. For example, poor oral hygiene can lead to periodontal disease, a condition characterized by inflammation and infection of the gums, which has been associated with an increased risk for cardiovascular problems like heart attack and stroke. Regular consultations and proper oral hygiene maintenance help prevent such complications.\n\nAdditionally, the information provided indicates that effective medication management is in place through multiple instances of medication reconciliation, ensuring there are no adverse drug interactions. This further supports a comprehensive approach to health care, contributing positively to overall well-being by addressing both preventive measures (like not smoking and regular dental check-ups) and proactive management of any ongoing medical conditions or medications.\n\nIn summary, the combination of never smoking tobacco and maintaining regular dental care significantly enhances the patient's overall health status through the reduction of risks associated with smoking and oral disease, which can lead to improved systemic health outcomes."
    },
    {
        "file": "temp/flat/Ettie537_Farrell962_d8638449-e632-1ac7-6695-eb60c8773813/Ettie537_Farrell962_d8638449-e632-1ac7-6695-eb60c8773813_09-08-2020.txt",
        "query": "How tall was Ettie537 Farrell962 at the time of her medical encounter, and what pain severity score did she report?",
        "synthetic query": "What was the range of heights and reported pain severity scores during medical encounters for a patient?",
        "information": [
            "Here is the information regarding Ettie537 Farrell962's height and pain severity scores at various medical encounters:\n\n- **Encounter Date: 15-08-2021**\n    - Body Height: 118.60 cm\n    - Pain severity (Score): 2.00\n\n- **Encounter Date: 29-07-2018**\n    - Body Height: 100.20 cm\n    - Pain severity (Score): 1.00\n\n- **Encounter Date: 09-08-2020**\n    - Body Height: 113.00 cm\n    - Pain severity (Score): 3.00\n\n- **Encounter Date: 24-07-2016**\n    - Body Height: 87.60 cm\n    - Pain severity (Score): 2.00\n\n- **Encounter Date: 01-09-2024**\n    - Body Height: 133.00 cm\n    - Pain severity (Score): 3.00\n\n- **Encounter Date: 04-08-2019**\n    - Body Height: 106.80 cm\n    - Pain severity (Score): 1.00"
        ],
        "nodes": [
            "Ettie537_Farrell962_d8638449-e632-1ac7-6695-eb60c8773813_15-08-2021.txt",
            "Ettie537_Farrell962_d8638449-e632-1ac7-6695-eb60c8773813_29-07-2018.txt",
            "Ettie537_Farrell962_d8638449-e632-1ac7-6695-eb60c8773813_09-08-2020.txt",
            "Ettie537_Farrell962_d8638449-e632-1ac7-6695-eb60c8773813_24-07-2016.txt",
            "Ettie537_Farrell962_d8638449-e632-1ac7-6695-eb60c8773813_01-09-2024.txt",
            "Ettie537_Farrell962_d8638449-e632-1ac7-6695-eb60c8773813_04-08-2019.txt"
        ],
        "synthesized information": "The patient had a range of heights during medical encounters from 87.60 cm to 133.00 cm, and reported pain severity scores ranging from 1.00 to 3.00.",
        "review": "The response should summarize the patient's height and pain severity score at their latest medical encounter, rather than providing a range over all encounters.",
        "response": "The range of heights for the patient during medical encounters was from 87.60 cm to 133.00 cm, and the reported pain severity scores ranged from 1.00 to 3.00."
    },
    {
        "file": "temp/flat/Ettie537_Farrell962_d8638449-e632-1ac7-6695-eb60c8773813/Ettie537_Farrell962_d8638449-e632-1ac7-6695-eb60c8773813_09-08-2020.txt",
        "query": "Based on the observations, what was Ettie537 Farrell962's body mass index (BMI) percentile per age and sex as of the encounter date?",
        "synthetic query": "What was the patient's body mass index (BMI) percentile per age and sex as of the most recent encounter date?",
        "information": [
            "Here is the extracted Body Mass Index (BMI) Percentile data for Ettie537 Farrell962 from each encounter date:\n\n- Encounter Date: 01-09-2024, BMI [Percentile] Per age and sex Value: 66.99 %\n- Encounter Date: 09-08-2020, BMI [Percentile] Per age and sex Value: 71.72 %\n- Encounter Date: 23-07-2017, BMI [Percentile] Per age and sex Value: 88.40 %\n- Encounter Date: 22-01-2017, BMI [Percentile] Per age and sex Value: 93.99 %\n- Encounter Date: 24-07-2016, BMI [Percentile] Per age and sex Value: 92.41 %\n- Encounter Date: 24-01-2016, BMI [Percentile] Per age and sex Value: 87.85 %"
        ],
        "nodes": [
            "Ettie537_Farrell962_d8638449-e632-1ac7-6695-eb60c8773813_09-08-2020.txt",
            "Ettie537_Farrell962_d8638449-e632-1ac7-6695-eb60c8773813_22-01-2017.txt",
            "Ettie537_Farrell962_d8638449-e632-1ac7-6695-eb60c8773813_24-01-2016.txt",
            "Ettie537_Farrell962_d8638449-e632-1ac7-6695-eb60c8773813_24-07-2016.txt",
            "Ettie537_Farrell962_d8638449-e632-1ac7-6695-eb60c8773813_23-07-2017.txt",
            "Ettie537_Farrell962_d8638449-e632-1ac7-6695-eb60c8773813_01-09-2024.txt"
        ],
        "synthesized information": "The patient's BMI percentile per age and sex varied over time:\n- Encounter Date: 01-09-2024, BMI Percentile Value: 67%\n- Encounter Date: 09-08-2020, BMI Percentile Value: 72%\n- Encounter Date: 23-07-2017, BMI Percentile Value: 88%\n- Encounter Date: 22-01-2017, BMI Percentile Value: 94%\n- Encounter Date: 24-07-2016, BMI Percentile Value: 92%\n- Encounter Date: 24-01-2016, BMI Percentile Value: 88%",
        "review": "The synthesized information needs to include specific encounter dates to make it complete. The patient's BMI percentile values should be presented with their corresponding encounter dates for a clear understanding.",
        "response": "Based on the most recent encounter date provided (01-09-2024), the patient's BMI percentile per age and sex was 67%."
    },
    {
        "file": "temp/flat/Ettie537_Farrell962_d8638449-e632-1ac7-6695-eb60c8773813/Ettie537_Farrell962_d8638449-e632-1ac7-6695-eb60c8773813_09-08-2020.txt",
        "query": "What were Ettie537 Farrell962's systolic and diastolic blood pressure readings during the medical examination on 09-08-2020?",
        "synthetic query": "What were the systolic and diastolic blood pressure readings during the medical examination on [DATE]?",
        "information": [
            "Ettie537 Farrell962's systolic blood pressure reading on 09-08-2020 was 106.00 mm[Hg] and the diastolic reading was 85.00 mm[Hg]."
        ],
        "nodes": [
            "Ettie537_Farrell962_d8638449-e632-1ac7-6695-eb60c8773813_09-08-2020.txt",
            "Ettie537_Farrell962_d8638449-e632-1ac7-6695-eb60c8773813_24-05-2020.txt",
            "Ettie537_Farrell962_d8638449-e632-1ac7-6695-eb60c8773813_04-08-2019.txt",
            "Ettie537_Farrell962_d8638449-e632-1ac7-6695-eb60c8773813_15-08-2021.txt",
            "Ettie537_Farrell962_d8638449-e632-1ac7-6695-eb60c8773813_21-08-2022.txt"
        ],
        "synthesized information": "The patient's systolic blood pressure reading on [DATE] was 106 mm[Hg], and the diastolic reading was 85 mm[Hg].",
        "review": "The response contains the correct systolic and diastolic blood pressure readings but lacks the date of the examination. The information should be presented clearly with all necessary details.",
        "response": "The systolic blood pressure reading during the medical examination on [DATE] was 106 mm[Hg], and the diastolic reading was 85 mm[Hg]."
    }
]